ufig/__init__.py
ufig/array_util.py
ufig/coordinate_util.py
ufig/io_util.py
ufig/mask_utils.py
ufig/rendering_util.py
ufig/run_util.py
ufig/sampling_util.py
ufig/se_moment_util.py
ufig/sysmaps_util.py
ufig/workflow_util.py
ufig/config/__init__.py
ufig/config/common.py
ufig/config/test_config.py
ufig/config/test_config_adv.py
ufig/plugins/__init__.py
ufig/plugins/add_generic_stamp_flags.py
ufig/plugins/add_generic_stamp_flags_ucat.py
ufig/plugins/add_lensing.py
ufig/plugins/add_psf.py
ufig/plugins/background_noise.py
ufig/plugins/background_subtract.py
ufig/plugins/cleanup_catalogs.py
ufig/plugins/cleanup_memory.py
ufig/plugins/compression_noise.py
ufig/plugins/convert_photons_to_adu.py
ufig/plugins/draw_stars_besancon_map.py
ufig/plugins/estimate_psf.py
ufig/plugins/gamma_interpolation_table.py
ufig/plugins/match_sextractor_catalog_multiband_read.py
ufig/plugins/match_sextractor_seg_catalog_multiband_read.py
ufig/plugins/multi_band_setup.py
ufig/plugins/read_in_catalog.py
ufig/plugins/render_galaxies_flexion.py
ufig/plugins/render_stars_photon.py
ufig/plugins/resample.py
ufig/plugins/run_detection_classifier.py
ufig/plugins/run_emulator.py
ufig/plugins/run_nflow.py
ufig/plugins/run_sextractor.py
ufig/plugins/run_sextractor_forced_photometry.py
ufig/plugins/saturate_pixels.py
ufig/plugins/saturate_pixels_x.py
ufig/plugins/single_band_setup.py
ufig/plugins/single_band_setup_intrinsic_only.py
ufig/plugins/write_catalog.py
ufig/plugins/write_catalog_for_emu.py
ufig/plugins/write_image.py
ufig/psf_estimation/__init__.py
ufig/psf_estimation/cnn_predictions.py
ufig/psf_estimation/cnn_util.py
ufig/psf_estimation/core.py
ufig/psf_estimation/correct_brighter_fatter.py
ufig/psf_estimation/cutouts_utils.py
ufig/psf_estimation/data_preparation.py
ufig/psf_estimation/polynomial_fitting.py
ufig/psf_estimation/psf_predictions.py
ufig/psf_estimation/psf_utils.py
ufig/psf_estimation/save_model.py
ufig/psf_estimation/star_sample_selection_cnn.py
ufig/psf_estimation/tiled_regressor.py
ufig-1.1.0.dist-info/METADATA
ufig-1.1.0.dist-info/WHEEL
ufig-1.1.0.dist-info/licenses/AUTHORS.rst
ufig-1.1.0.dist-info/licenses/LICENSE.txt
ufig-1.1.0.dist-info/RECORD
