Metadata-Version: 2.4
Name: ufig
Version: 1.1.0
Summary: Package for fast image simulations
Project-URL: Source, https://gitlab.com/cosmology-ethz/ufig
Project-URL: Documentation, https://cosmo-docs.phys.ethz.ch/ufig
Author: Silvan Fischbacher, Beatrice Moser, Tomasz Kacprzak, Joerg Herbel, Claudio Bruderer, Joel Akeret, Lukas Gamper, Joel Berge, Luca Tortorelli, Uwe Schmitt
License: MIT License
License-File: AUTHORS.rst
License-File: LICENSE.txt
Classifier: Intended Audience :: Developers
Classifier: Intended Audience :: Science/Research
Classifier: License :: OSI Approved :: MIT License
Classifier: Natural Language :: English
Classifier: Operating System :: OS Independent
Classifier: Programming Language :: Python :: 3
Classifier: Programming Language :: Python :: 3.9
Classifier: Programming Language :: Python :: 3.10
Classifier: Programming Language :: Python :: 3.11
Classifier: Programming Language :: Python :: 3.12
Requires-Dist: astropy>=6.0.1
Requires-Dist: cosmic-toolbox>=0.3.1
Requires-Dist: cosmo-torrent
Requires-Dist: darkskysync>=0.2.0
Requires-Dist: h5py>=3.12.1
Requires-Dist: healpy
Requires-Dist: ivy-wfengine>=0.4.0
Requires-Dist: numba>=0.60.0
Requires-Dist: numpy
Requires-Dist: scikit-learn
Requires-Dist: scipy
Requires-Dist: tensorflow
